python_slurm/__init__.py
python_slurm/job.py
python_slurm-0.0.1.dist-info/METADATA
python_slurm-0.0.1.dist-info/WHEEL
python_slurm-0.0.1.dist-info/licenses/LICENSE
python_slurm-0.0.1.dist-info/RECORD
