Metadata-Version: 2.4
Name: python_slurm
Version: 0.0.1
Summary: A small python package to launch slurm jobs
Project-URL: Homepage, https://github.com/cecilpert/py_slurm
Project-URL: Issues, https://github.com/cecilpert/py_slurm/issues
Author-email: Cecil Hilpert <cecile.hilpert@cnrs.fr>
License-Expression: CECILL-2.1
License-File: LICENSE
Classifier: Programming Language :: Python :: 3
Requires-Python: >=3.9
